{"offset":0,"results":[{"paragrafe":["<p align=\"justify\">Dumnezeul nostru, nadejdea tuturor marginilor pamantului si a celor ce sunt pe mare departe, Cel ce mai inainte ai tocmit, prin Legea Ta cea Veche si cea Noua, aceste zile de post, la care ne-ai invrednicit sa ajungem acum, pe Tine Te laudam si Tie ne rugam: intareste-ne cu puterea Ta, ca sa ne nevoim intru ele cu sarguinta, spre marirea numelui Tau celui sfant si spre iertarea pacatelor noastre, spre omorarea patimilor si biruinta asupra pacatului,- ca impreuna cu Tine rastignindu-ne si ingropandu-ne, sa ne ridicam din faptele cele moarte si sa petrecem cu buna placere inaintea Ta intru toate zilele vietii noastre. Ca Tie se cuvine a ne milui si a ne mantui pe noi, Hristoase-Dumnezeule, si Tie slava inaltam, impreuna si Celui fara de inceput al Tau Parinte, si Preasfantului si bunului si de viata facatorului Tau Duh, acum si pururea si in vecii vecilor. Amin.</p>"]}],"cookies":["PHPSESSID=\"ac51mgevmdiacfiqqscnh74fi7\";Path=\"/\";Domain=\"www.crestinortodox.ro\";Port=\"80\"","CAKEPHP=\"ac51mgevmdiacfiqqscnh74fi7\";Path=\"/\";Domain=\"www.crestinortodox.ro\";Port=\"80\""],"connectorVersionGuid":"9b957a65-d3c4-4b77-92b3-64cc89dd24c8","connectorGuid":"d87410eb-0ccc-4938-8e01-5d6affd71986","pageUrl":"http://www.crestinortodox.ro/rugaciuni/rugaciune-care-citeste-fiecare-post-72568.html"}